OleFileIO_PL.py
olefile/CONTRIBUTORS.txt
olefile/LICENSE.txt
olefile/README.html
olefile/README.rst
olefile/__init__.py
olefile/olefile.html
olefile/olefile.py
olefile/olefile2.html
olefile/olefile2.py
olefile/doc/API.html
olefile/doc/API.md
olefile/doc/Contribute.html
olefile/doc/Contribute.md
olefile/doc/Home.html
olefile/doc/Home.md
olefile/doc/Install.html
olefile/doc/Install.md
olefile/doc/License.html
olefile/doc/License.md
olefile/doc/OLE_Overview.html
olefile/doc/OLE_Overview.md
olefile/doc/OLE_VBA_sample.png
olefile-0.47.dev4.dist-info/LICENSE.txt
olefile-0.47.dev4.dist-info/METADATA
olefile-0.47.dev4.dist-info/WHEEL
olefile-0.47.dev4.dist-info/top_level.txt
olefile-0.47.dev4.dist-info/RECORD
